s2_python-0.8.0.dist-info/licenses/LICENSE
s2python/__init__.py
s2python/message.py
s2python/py.typed
s2python/reception_status_awaiter.py
s2python/s2_connection.py
s2python/s2_control_type.py
s2python/s2_parser.py
s2python/s2_validation_error.py
s2python/utils.py
s2python/validate_values_mixin.py
s2python/version.py
s2python/common/__init__.py
s2python/common/duration.py
s2python/common/handshake.py
s2python/common/handshake_response.py
s2python/common/instruction_status_update.py
s2python/common/number_range.py
s2python/common/power_forecast.py
s2python/common/power_forecast_element.py
s2python/common/power_forecast_value.py
s2python/common/power_measurement.py
s2python/common/power_range.py
s2python/common/power_value.py
s2python/common/reception_status.py
s2python/common/resource_manager_details.py
s2python/common/revoke_object.py
s2python/common/role.py
s2python/common/select_control_type.py
s2python/common/session_request.py
s2python/common/support.py
s2python/common/timer.py
s2python/common/transition.py
s2python/ddbc/__init__.py
s2python/ddbc/ddbc_actuator_description.py
s2python/ddbc/ddbc_actuator_status.py
s2python/ddbc/ddbc_average_demand_rate_forecast.py
s2python/ddbc/ddbc_average_demand_rate_forecast_element.py
s2python/ddbc/ddbc_instruction.py
s2python/ddbc/ddbc_operation_mode.py
s2python/ddbc/ddbc_system_description.py
s2python/ddbc/ddbc_timer_status.py
s2python/frbc/__init__.py
s2python/frbc/frbc_actuator_description.py
s2python/frbc/frbc_actuator_status.py
s2python/frbc/frbc_fill_level_target_profile.py
s2python/frbc/frbc_fill_level_target_profile_element.py
s2python/frbc/frbc_instruction.py
s2python/frbc/frbc_leakage_behaviour.py
s2python/frbc/frbc_leakage_behaviour_element.py
s2python/frbc/frbc_operation_mode.py
s2python/frbc/frbc_operation_mode_element.py
s2python/frbc/frbc_storage_description.py
s2python/frbc/frbc_storage_status.py
s2python/frbc/frbc_system_description.py
s2python/frbc/frbc_timer_status.py
s2python/frbc/frbc_usage_forecast.py
s2python/frbc/frbc_usage_forecast_element.py
s2_python-0.8.0.dist-info/METADATA
s2_python-0.8.0.dist-info/WHEEL
s2_python-0.8.0.dist-info/entry_points.txt
s2_python-0.8.0.dist-info/top_level.txt
s2_python-0.8.0.dist-info/RECORD
